hub_client/__init__.py
hub_client/client.py
hub_client/connection.py
hub_client/types.py
hub_client/utils.py
phygrid_hub_client-0.1.0.dist-info/METADATA
phygrid_hub_client-0.1.0.dist-info/WHEEL
phygrid_hub_client-0.1.0.dist-info/RECORD
